string_encoder/__init__.py
string_encoder/decode.py
string_encoder/encode.py
string_encoder-0.0.1.dist-info/METADATA
string_encoder-0.0.1.dist-info/WHEEL
string_encoder-0.0.1.dist-info/licenses/LICENSE.txt
string_encoder-0.0.1.dist-info/RECORD
